setup.py
mashape_analytics.egg-info/PKG-INFO
mashape_analytics.egg-info/SOURCES.txt
mashape_analytics.egg-info/dependency_links.txt
mashape_analytics.egg-info/entry_points.txt
mashape_analytics.egg-info/not-zip-safe
mashape_analytics.egg-info/requires.txt
mashape_analytics.egg-info/top_level.txt
mashapeanalytics/__init__.py
mashapeanalytics/alf.py
mashapeanalytics/transport.py
mashapeanalytics/middleware/__init__.py
mashapeanalytics/middleware/django_middleware.py
mashapeanalytics/middleware/wsgi_middleware.py