Metadata-Version: 1.1
Name: mashape-analytics
Version: 1.1.0
Summary: Python Agent for Mashape Analytics
Home-page: https://github.com/Mashape/analytics-agent-python
Author: Mashape
Author-email: opensource@mashape.com
License: MIT
Download-URL: https://github.com/Mashape/analytics-agent-python/archive/v1.1.0.zip
Platform: UNKNOWN
Classifier: Environment :: Web Environment
Classifier: Intended Audience :: Developers
Classifier: Development Status :: 5 - Production/Stable
Classifier: License :: OSI Approved :: MIT License
Classifier: Operating System :: OS Independent
Classifier: Programming Language :: Python
Classifier: Programming Language :: Python :: 3
Classifier: Topic :: Internet :: WWW/HTTP :: Dynamic Content
Classifier: Topic :: Software Development :: Libraries :: Python Modules
Classifier: Topic :: Utilities
